verilog/rtl/mbisr_controller.v
module mbisr_controller #(
    parameter ADDR_WIDTH = 8,
    parameter DATA_WIDTH = 8,
    parameter MAX_REPAIRS = 16,
    parameter SPARE_BASE = 8'hF0
)(
    input clk,
    input rst,
    // MBIST failure event input (captures addresses)
    input bist_fail_valid,
    input [ADDR_WIDTH-1:0] bist_fail_addr,
    // user memory interface
    input [ADDR_WIDTH-1:0] user_addr,
    input [DATA_WIDTH-1:0] user_wdata,
    input user_we,
    input user_en,
    output [DATA_WIDTH-1:0] user_rdata,
    // remapped memory interface to underlying RAM
    output [ADDR_WIDTH-1:0] mem_addr,
    output [DATA_WIDTH-1:0] mem_wdata,
    output mem_we,
    output mem_en,
    input [DATA_WIDTH-1:0] mem_rdata
);
    // repair table
    reg [ADDR_WIDTH-1:0] repair_table [0:MAX_REPAIRS-1];
    reg repair_valid [0:MAX_REPAIRS-1];
    integer i, j;
    initial begin
        for (i=0; i<MAX_REPAIRS; i=i+1) begin
            repair_table[i] = {ADDR_WIDTH{1'b1}}; // invalid default (all ones)
            repair_valid[i] = 1'b0;
        end
    end

    // capture failures (store unique addresses)
    reg inserted;
    always @(posedge clk or posedge rst) begin
        if (rst) begin
            for (i=0;i<MAX_REPAIRS;i=i+1) begin
                repair_table[i] <= {ADDR_WIDTH{1'b1}};
                repair_valid[i] <= 1'b0;
            end
        end else begin
            if (bist_fail_valid) begin
                inserted = 1'b0;
                // check duplicate
                for (j=0;j<MAX_REPAIRS;j=j+1) begin
                    if (repair_valid[j] && repair_table[j] == bist_fail_addr) begin
                        inserted = 1'b1;
                    end
                end
                if (!inserted) begin
                    for (j=0;j<MAX_REPAIRS;j=j+1) begin
                        if (!repair_valid[j] && !inserted) begin
                            repair_table[j] <= bist_fail_addr;
                            repair_valid[j] <= 1'b1;
                            inserted = 1'b1;
                        end
                    end
                end
            end
        end
    end

    // CAM-like remap combinational lookup
    reg [ADDR_WIDTH-1:0] remap_addr;
    integer k;
    always @(*) begin
        remap_addr = user_addr;
        for (k=0;k<MAX_REPAIRS;k=k+1) begin
            if (repair_valid[k] && repair_table[k] == user_addr) begin
                remap_addr = SPARE_BASE + k[ADDR_WIDTH-1:0];
            end
        end
    end

    assign mem_addr = remap_addr;
    assign mem_wdata = user_wdata;
    assign mem_we = user_we;
    assign mem_en = user_en;
    assign user_rdata = mem_rdata;

endmodule

verilog/rtl/mbist_controller.v
module mbist_controller (
    input        clk,
    input        rst,
    input        start,
    output reg   done,
    output reg   fail,
    output reg   fail_valid,
    output reg [7:0] fail_addr,

    output reg       mem_we,
    output reg [7:0] mem_addr,
    output reg [7:0] mem_wdata,
    input      [7:0] mem_rdata
);
    reg [3:0]  state;
    reg [7:0] addr;
    reg [7:0] expected;
    integer i;

    always @(posedge clk or posedge rst) begin
        if (rst) begin
            state      <= 0;
            addr       <= 0;
            done       <= 0;
            fail       <= 0;
            fail_valid <= 0;
            mem_we     <= 0;
            mem_addr   <= 0;
            mem_wdata  <= 0;
            expected   <= 0;
        end else begin
            // default outputs
            fail_valid <= 0;
            mem_we <= 0;

            case (state)
                0: begin
                    if (start) begin
                        addr  <= 0;
                        done  <= 0;
                        fail  <= 0;
                        state <= 1;
                    end
                end

                1: begin // write 0
                    mem_we    <= 1;
                    mem_addr  <= addr;
                    mem_wdata <= 8'h00;
                    state     <= 2;
                end

                2: begin // read back
                    mem_we    <= 0;
                    mem_addr  <= addr;
                    expected  <= 8'h00;
                    state     <= 3;
                end

                3: begin // compare and move next
                    if (mem_rdata !== expected) begin
                        fail       <= 1;
                        fail_valid <= 1;
                        fail_addr  <= addr;
                    end
                    if (addr == 8'hFF) begin
                        state <= 4;
                    end else begin
                        addr  <= addr + 1;
                        state <= 1;
                    end
                end

                4: begin
                    done <= 1;
                    state <= 4;
                end
            endcase
        end
    end
endmodule

verilog/rtl/top.v
module top (
    input clk,
    input rst,
    input start,
    output done,
    output fail
);
    // MBIST instance wires
    wire mem_we_mbist;
    wire [7:0] mem_addr_mbist;
    wire [7:0] mem_wdata_mbist;
    wire [7:0] mem_rdata_mbist;
    wire fail_valid_mbist;
    wire [7:0] fail_addr_mbist;

    mbist_controller mbist0 (
        .clk(clk),
        .rst(rst),
        .start(start),
        .done(done),
        .fail(fail),
        .fail_valid(fail_valid_mbist),
        .fail_addr(fail_addr_mbist),
        .mem_we(mem_we_mbist),
        .mem_addr(mem_addr_mbist),
        .mem_wdata(mem_wdata_mbist),
        .mem_rdata(mem_rdata_mbist)
    );

    // MBISR instance wires (user side left mostly unused in this demo)
    wire [7:0] user_rdata;
    wire [7:0] mem_addr_mbisr;
    wire [7:0] mem_wdata_mbisr;
    wire mem_we_mbisr;
    wire mem_en_mbisr;

    mbisr_controller #(.ADDR_WIDTH(8), .DATA_WIDTH(8), .MAX_REPAIRS(16), .SPARE_BASE(8'hF0)) mbisr0 (
        .clk(clk),
        .rst(rst),
        .bist_fail_valid(fail_valid_mbist),
        .bist_fail_addr(fail_addr_mbist),
        .user_addr(8'h00),
        .user_wdata(8'h00),
        .user_we(1'b0),
        .user_en(1'b0),
        .user_rdata(user_rdata),
        .mem_addr(mem_addr_mbisr),
        .mem_wdata(mem_wdata_mbisr),
        .mem_we(mem_we_mbisr),
        .mem_en(mem_en_mbisr),
        .mem_rdata(mem_rdata_mbist)
    );

    // For user-controlled fault injection: expose regs that TB can set hierarchically
    reg fault_en;
    reg [7:0] fault_addr;
    initial begin
        fault_en = 1'b0;
        fault_addr = 8'h00;
    end

    // Simple arbitration: MBIST drives the RAM; MBISR/user signals not used for writes in this demo.
    wire final_we = mem_we_mbist;
    wire [7:0] final_addr = mem_addr_mbist;
    wire [7:0] final_wdata = mem_wdata_mbist;
    wire final_en = mem_we_mbist; // MBIST always writes then reads

    // synchronous RAM
    reg [7:0] ram [0:255];
    reg [7:0] ram_out;
    integer i;
    initial begin
        for (i=0;i<256;i=i+1) ram[i] = 8'h00;
    end

    always @(posedge clk) begin
        if (final_en && final_we) begin
            ram[final_addr] <= final_wdata;
        end
        ram_out <= ram[final_addr];
    end

    // fault injection on read: if fault_en and address matches, force LSB = 0 (stuck-at-0 example)
    wire fault_match = fault_en && (final_addr == fault_addr);
    wire [7:0] mem_rdata_comb = fault_match ? {ram_out[7:1], 1'b0} : ram_out;

    assign mem_rdata_mbist = mem_rdata_comb;

    // expose the fault control regs for hierarchical access by testbench
    // In TB: DUT.dut.fault_en = 1; DUT.dut.fault_addr = 8;
endmodule

verilog/rtl/tt_hp_um_aksp_mbist_mbisr.v
// Top-level TinyTapeout-HP wrapper (user module)
module tt_hp_um_aksp_mbist_mbisr (
    input wire clk,
    input wire rst,
    input wire start,
    output wire done,
    output wire fail
);
    top dut (
        .clk(clk),
        .rst(rst),
        .start(start),
        .done(done),
        .fail(fail)
    );
endmodule

sim/tb_top.v
module tb_top;
    reg clk;
    reg rst;
    reg start;

    wire done;
    wire fail;

    // instantiate wrapper
    tt_hp_um_aksp_mbist_mbisr dut (
        .clk(clk),
        .rst(rst),
        .start(start),
        .done(done),
        .fail(fail)
    );

    initial begin
        clk = 0;
        forever #5 clk = ~clk;
    end

    initial begin
        $dumpfile("wave.vcd");
        $dumpvars(0, tb_top);

        rst = 1; start = 0;
        #20 rst = 0; #20;

        // inject a fault at address 8 (example) via hierarchical access
        // set regs inside top through the wrapper: dut.dut.fault_en = 1; dut.dut.fault_addr = 8;
        dut.dut.fault_en = 1;
        dut.dut.fault_addr = 8;

        // run MBIST
        start = 1; #10; start = 0;

        // wait for completion
        wait (done == 1);
        $display("MBIST complete. fail=%0d", fail);

        // change fault location and re-run
        #50;
        dut.dut.fault_en = 1;
        dut.dut.fault_addr = 42;

        start = 1; #10; start = 0;
        wait (done == 1);
        $display("MBIST second run complete. fail=%0d", fail);

        #100;
        $finish;
    end
endmodule

verilog/rtl/wave.vcd
$date
	Wed Dec 03 14:16:50 2025
$end
$version
	Icarus Verilog
$end
$timescale
	1s
$end
$scope module tb_top $end
$var wire 1 ! fail $end
$var wire 1 " done $end
$var reg 1 # clk $end
$var reg 1 $ rst $end
$var reg 1 % start $end
$scope module dut $end
$var wire 1 # clk $end
$var wire 1 $ rst $end
$var wire 1 % start $end
$var wire 1 ! fail $end
$var wire 1 " done $end
$scope module dut $end
$var wire 1 # clk $end
$var wire 1 & fault_match $end
$var wire 8 ' final_addr [7:0] $end
$var wire 1 ( final_en $end
$var wire 8 ) final_wdata [7:0] $end
$var wire 1 * final_we $end
$var wire 8 + mem_rdata_mbist [7:0] $end
$var wire 1 $ rst $end
$var wire 1 % start $end
$var wire 8 , user_rdata [7:0] $end
$var wire 1 - mem_we_mbist $end
$var wire 1 . mem_we_mbisr $end
$var wire 8 / mem_wdata_mbist [7:0] $end
$var wire 8 0 mem_wdata_mbisr [7:0] $end
$var wire 8 1 mem_rdata_comb [7:0] $end
$var wire 1 2 mem_en_mbisr $end
$var wire 8 3 mem_addr_mbist [7:0] $end
$var wire 8 4 mem_addr_mbisr [7:0] $end
$var wire 1 5 fail_valid_mbist $end
$var wire 8 6 fail_addr_mbist [7:0] $end
$var wire 1 ! fail $end
$var wire 1 " done $end
$var reg 8 7 fault_addr [7:0] $end
$var reg 1 8 fault_en $end
$var reg 8 9 ram_out [7:0] $end
$var integer 32 : i [31:0] $end
$scope module mbisr0 $end
$var wire 1 # clk $end
$var wire 8 ; mem_addr [7:0] $end
$var wire 1 2 mem_en $end
$var wire 8 < mem_rdata [7:0] $end
$var wire 8 = mem_wdata [7:0] $end
$var wire 1 . mem_we $end
$var wire 1 $ rst $end
$var wire 8 > user_addr [7:0] $end
$var wire 1 ? user_en $end
$var wire 8 @ user_rdata [7:0] $end
$var wire 8 A user_wdata [7:0] $end
$var wire 1 B user_we $end
$var wire 1 5 bist_fail_valid $end
$var wire 8 C bist_fail_addr [7:0] $end
$var parameter 32 D ADDR_WIDTH $end
$var parameter 32 E DATA_WIDTH $end
$var parameter 32 F MAX_REPAIRS $end
$var parameter 8 G SPARE_BASE $end
$var reg 1 H inserted $end
$var reg 8 I remap_addr [7:0] $end
$var integer 32 J i [31:0] $end
$var integer 32 K j [31:0] $end
$var integer 32 L k [31:0] $end
$upscope $end
$scope module mbist0 $end
$var wire 1 # clk $end
$var wire 8 M mem_rdata [7:0] $end
$var wire 1 $ rst $end
$var wire 1 % start $end
$var reg 8 N addr [7:0] $end
$var reg 1 " done $end
$var reg 8 O expected [7:0] $end
$var reg 1 ! fail $end
$var reg 8 P fail_addr [7:0] $end
$var reg 1 5 fail_valid $end
$var reg 8 Q mem_addr [7:0] $end
$var reg 8 R mem_wdata [7:0] $end
$var reg 1 - mem_we $end
$var reg 4 S state [3:0] $end
$upscope $end
$upscope $end
$upscope $end
$upscope $end
$enddefinitions $end
$comment Show the parameter values. $end
$dumpall
b11110000 G
b10000 F
b1000 E
b1000 D
$end
#0
$dumpvars
b0 S
b0 R
b0 Q
bx P
b0 O
b0 N
bx M
b10000 L
bx K
b10000 J
b0 I
xH
bx C
0B
b0 A
bx @
0?
b0 >
b0 =
bx <
b0 ;
b100000000 :
bx 9
08
b0 7
bx 6
05
b0 4
b0 3
02
bx 1
b0 0
b0 /
0.
0-
bx ,
bx +
0*
b0 )
0(
b0 '
0&
0%
1$
0#
0"
0!
$end
#5
b0 ,
b0 @
b0 +
b0 <
b0 M
b0 1
b0 9
b10000 J
1#
#10
0#
#15
b10000 J
1#
#20
0#
0$
#25
1#
#30
0#
#35
1#
#40
0#
1%
b1000 7
18
#45
b1 S
1#
#50
0#
0%
#55
b10 S
1(
1*
1-
1#
#60
0#
#65
b11 S
0(
0*
0-
1#
#70
0#
#75
b1 S
b1 N
1#
#80
0#
#85
b10 S
b1 '
b1 3
b1 Q
1(
1*
1-
1#
#90
0#
#95
b11 S
0(
0*
0-
1#
#100
0#
#105
b1 S
b10 N
1#
#110
0#
#115
b10 S
b10 '
b10 3
b10 Q
1(
1*
1-
1#
#120
0#
#125
b11 S
0(
0*
0-
1#
#130
0#
#135
b1 S
b11 N
1#
#140
0#
#145
b10 S
b11 '
b11 3
b11 Q
1(
1*
1-
1#
#150
0#
#155
b11 S
0(
0*
0-
1#
#160
0#
#165
b1 S
b100 N
1#
#170
0#
#175
b10 S
b100 '
b100 3
b100 Q
1(
1*
1-
1#
#180
0#
#185
b11 S
0(
0*
0-
1#
#190
0#
#195
b1 S
b101 N
1#
#200
0#
#205
b10 S
b101 '
b101 3
b101 Q
1(
1*
1-
1#
#210
0#
#215
b11 S
0(
0*
0-
1#
#220
0#
#225
b1 S
b110 N
1#
#230
0#
#235
b10 S
b110 '
b110 3
b110 Q
1(
1*
1-
1#
#240
0#
#245
b11 S
0(
0*
0-
1#
#250
0#
#255
b1 S
b111 N
1#
#260
0#
#265
b10 S
b111 '
b111 3
b111 Q
1(
1*
1-
1#
#270
0#
#275
b11 S
0(
0*
0-
1#
#280
0#
#285
b1 S
b1000 N
1#
#290
0#
#295
1&
b10 S
b1000 '
b1000 3
b1000 Q
1(
1*
1-
1#
#300
0#
#305
b11 S
0(
0*
0-
1#
#310
0#
#315
b1 S
b1001 N
1#
#320
0#
#325
0&
b10 S
b1001 '
b1001 3
b1001 Q
1(
1*
1-
1#
#330
0#
#335
b11 S
0(
0*
0-
1#
#340
0#
#345
b1 S
b1010 N
1#
#350
0#
#355
b10 S
b1010 '
b1010 3
b1010 Q
1(
1*
1-
1#
#360
0#
#365
b11 S
0(
0*
0-
1#
#370
0#
#375
b1 S
b1011 N
1#
#380
0#
#385
b10 S
b1011 '
b1011 3
b1011 Q
1(
1*
1-
1#
#390
0#
#395
b11 S
0(
0*
0-
1#
#400
0#
#405
b1 S
b1100 N
1#
#410
0#
#415
b10 S
b1100 '
b1100 3
b1100 Q
1(
1*
1-
1#
#420
0#
#425
b11 S
0(
0*
0-
1#
#430
0#
#435
b1 S
b1101 N
1#
#440
0#
#445
b10 S
b1101 '
b1101 3
b1101 Q
1(
1*
1-
1#
#450
0#
#455
b11 S
0(
0*
0-
1#
#460
0#
#465
b1 S
b1110 N
1#
#470
0#
#475
b10 S
b1110 '
b1110 3
b1110 Q
1(
1*
1-
1#
#480
0#
#485
b11 S
0(
0*
0-
1#
#490
0#
#495
b1 S
b1111 N
1#
#500
0#
#505
b10 S
b1111 '
b1111 3
b1111 Q
1(
1*
1-
1#
#510
0#
#515
b11 S
0(
0*
0-
1#
#520
0#
#525
b1 S
b10000 N
1#
#530
0#
#535
b10 S
b10000 '
b10000 3
b10000 Q
1(
1*
1-
1#
#540
0#
#545
b11 S
0(
0*
0-
1#
#550
0#
#555
b1 S
b10001 N
1#
#560
0#
#565
b10 S
b10001 '
b10001 3
b10001 Q
1(
1*
1-
1#
#570
0#
#575
b11 S
0(
0*
0-
1#
#580
0#
#585
b1 S
b10010 N
1#
#590
0#
#595
b10 S
b10010 '
b10010 3
b10010 Q
1(
1*
1-
1#
#600
0#
#605
b11 S
0(
0*
0-
1#
#610
0#
#615
b1 S
b10011 N
1#
#620
0#
#625
b10 S
b10011 '
b10011 3
b10011 Q
1(
1*
1-
1#
#630
0#
#635
b11 S
0(
0*
0-
1#
#640
0#
#645
b1 S
b10100 N
1#
#650
0#
#655
b10 S
b10100 '
b10100 3
b10100 Q
1(
1*
1-
1#
#660
0#
#665
b11 S
0(
0*
0-
1#
#670
0#
#675
b1 S
b10101 N
1#
#680
0#
#685
b10 S
b10101 '
b10101 3
b10101 Q
1(
1*
1-
1#
#690
0#
#695
b11 S
0(
0*
0-
1#
#700
0#
#705
b1 S
b10110 N
1#
#710
0#
#715
b10 S
b10110 '
b10110 3
b10110 Q
1(
1*
1-
1#
#720
0#
#725
b11 S
0(
0*
0-
1#
#730
0#
#735
b1 S
b10111 N
1#
#740
0#
#745
b10 S
b10111 '
b10111 3
b10111 Q
1(
1*
1-
1#
#750
0#
#755
b11 S
0(
0*
0-
1#
#760
0#
#765
b1 S
b11000 N
1#
#770
0#
#775
b10 S
b11000 '
b11000 3
b11000 Q
1(
1*
1-
1#
#780
0#
#785
b11 S
0(
0*
0-
1#
#790
0#
#795
b1 S
b11001 N
1#
#800
0#
#805
b10 S
b11001 '
b11001 3
b11001 Q
1(
1*
1-
1#
#810
0#
#815
b11 S
0(
0*
0-
1#
#820
0#
#825
b1 S
b11010 N
1#
#830
0#
#835
b10 S
b11010 '
b11010 3
b11010 Q
1(
1*
1-
1#
#840
0#
#845
b11 S
0(
0*
0-
1#
#850
0#
#855
b1 S
b11011 N
1#
#860
0#
#865
b10 S
b11011 '
b11011 3
b11011 Q
1(
1*
1-
1#
#870
0#
#875
b11 S
0(
0*
0-
1#
#880
0#
#885
b1 S
b11100 N
1#
#890
0#
#895
b10 S
b11100 '
b11100 3
b11100 Q
1(
1*
1-
1#
#900
0#
#905
b11 S
0(
0*
0-
1#
#910
0#
#915
b1 S
b11101 N
1#
#920
0#
#925
b10 S
b11101 '
b11101 3
b11101 Q
1(
1*
1-
1#
#930
0#
#935
b11 S
0(
0*
0-
1#
#940
0#
#945
b1 S
b11110 N
1#
#950
0#
#955
b10 S
b11110 '
b11110 3
b11110 Q
1(
1*
1-
1#
#960
0#
#965
b11 S
0(
0*
0-
1#
#970
0#
#975
b1 S
b11111 N
1#
#980
0#
#985
b10 S
b11111 '
b11111 3
b11111 Q
1(
1*
1-
1#
#990
0#
#995
b11 S
0(
0*
0-
1#
#1000
0#
#1005
b1 S
b100000 N
1#
#1010
0#
#1015
b10 S
b100000 '
b100000 3
b100000 Q
1(
1*
1-
1#
#1020
0#
#1025
b11 S
0(
0*
0-
1#
#1030
0#
#1035
b1 S
b100001 N
1#
#1040
0#
#1045
b10 S
b100001 '
b100001 3
b100001 Q
1(
1*
1-
1#
#1050
0#
#1055
b11 S
0(
0*
0-
1#
#1060
0#
#1065
b1 S
b100010 N
1#
#1070
0#
#1075
b10 S
b100010 '
b100010 3
b100010 Q
1(
1*
1-
1#
#1080
0#
#1085
b11 S
0(
0*
0-
1#
#1090
0#
#1095
b1 S
b100011 N
1#
#1100
0#
#1105
b10 S
b100011 '
b100011 3
b100011 Q
1(
1*
1-
1#
#1110
0#
#1115
b11 S
0(
0*
0-
1#
#1120
0#
#1125
b1 S
b100100 N
1#
#1130
0#
#1135
b10 S
b100100 '
b100100 3
b100100 Q
1(
1*
1-
1#
#1140
0#
#1145
b11 S
0(
0*
0-
1#
#1150
0#
#1155
b1 S
b100101 N
1#
#1160
0#
#1165
b10 S
b100101 '
b100101 3
b100101 Q
1(
1*
1-
1#
#1170
0#
#1175
b11 S
0(
0*
0-
1#
#1180
0#
#1185
b1 S
b100110 N
1#
#1190
0#
#1195
b10 S
b100110 '
b100110 3
b100110 Q
1(
1*
1-
1#
#1200
0#
#1205
b11 S
0(
0*
0-
1#
#1210
0#
#1215
b1 S
b100111 N
1#
#1220
0#
#1225
b10 S
b100111 '
b100111 3
b100111 Q
1(
1*
1-
1#
#1230
0#
#1235
b11 S
0(
0*
0-
1#
#1240
0#
#1245
b1 S
b101000 N
1#
#1250
0#
#1255
b10 S
b101000 '
b101000 3
b101000 Q
1(
1*
1-
1#
#1260
0#
#1265
b11 S
0(
0*
0-
1#
#1270
0#
#1275
b1 S
b101001 N
1#
#1280
0#
#1285
b10 S
b101001 '
b101001 3
b101001 Q
1(
1*
1-
1#
#1290
0#
#1295
b11 S
0(
0*
0-
1#
#1300
0#
#1305
b1 S
b101010 N
1#
#1310
0#
#1315
b10 S
b101010 '
b101010 3
b101010 Q
1(
1*
1-
1#
#1320
0#
#1325
b11 S
0(
0*
0-
1#
#1330
0#
#1335
b1 S
b101011 N
1#
#1340
0#
#1345
b10 S
b101011 '
b101011 3
b101011 Q
1(
1*
1-
1#
#1350
0#
#1355
b11 S
0(
0*
0-
1#
#1360
0#
#1365
b1 S
b101100 N
1#
#1370
0#
#1375
b10 S
b101100 '
b101100 3
b101100 Q
1(
1*
1-
1#
#1380
0#
#1385
b11 S
0(
0*
0-
1#
#1390
0#
#1395
b1 S
b101101 N
1#
#1400
0#
#1405
b10 S
b101101 '
b101101 3
b101101 Q
1(
1*
1-
1#
#1410
0#
#1415
b11 S
0(
0*
0-
1#
#1420
0#
#1425
b1 S
b101110 N
1#
#1430
0#
#1435
b10 S
b101110 '
b101110 3
b101110 Q
1(
1*
1-
1#
#1440
0#
#1445
b11 S
0(
0*
0-
1#
#1450
0#
#1455
b1 S
b101111 N
1#
#1460
0#
#1465
b10 S
b101111 '
b101111 3
b101111 Q
1(
1*
1-
1#
#1470
0#
#1475
b11 S
0(
0*
0-
1#
#1480
0#
#1485
b1 S
b110000 N
1#
#1490
0#
#1495
b10 S
b110000 '
b110000 3
b110000 Q
1(
1*
1-
1#
#1500
0#
#1505
b11 S
0(
0*
0-
1#
#1510
0#
#1515
b1 S
b110001 N
1#
#1520
0#
#1525
b10 S
b110001 '
b110001 3
b110001 Q
1(
1*
1-
1#
#1530
0#
#1535
b11 S
0(
0*
0-
1#
#1540
0#
#1545
b1 S
b110010 N
1#
#1550
0#
#1555
b10 S
b110010 '
b110010 3
b110010 Q
1(
1*
1-
1#
#1560
0#
#1565
b11 S
0(
0*
0-
1#
#1570
0#
#1575
b1 S
b110011 N
1#
#1580
0#
#1585
b10 S
b110011 '
b110011 3
b110011 Q
1(
1*
1-
1#
#1590
0#
#1595
b11 S
0(
0*
0-
1#
#1600
0#
#1605
b1 S
b110100 N
1#
#1610
0#
#1615
b10 S
b110100 '
b110100 3
b110100 Q
1(
1*
1-
1#
#1620
0#
#1625
b11 S
0(
0*
0-
1#
#1630
0#
#1635
b1 S
b110101 N
1#
#1640
0#
#1645
b10 S
b110101 '
b110101 3
b110101 Q
1(
1*
1-
1#
#1650
0#
#1655
b11 S
0(
0*
0-
1#
#1660
0#
#1665
b1 S
b110110 N
1#
#1670
0#
#1675
b10 S
b110110 '
b110110 3
b110110 Q
1(
1*
1-
1#
#1680
0#
#1685
b11 S
0(
0*
0-
1#
#1690
0#
#1695
b1 S
b110111 N
1#
#1700
0#
#1705
b10 S
b110111 '
b110111 3
b110111 Q
1(
1*
1-
1#
#1710
0#
#1715
b11 S
0(
0*
0-
1#
#1720
0#
#1725
b1 S
b111000 N
1#
#1730
0#
#1735
b10 S
b111000 '
b111000 3
b111000 Q
1(
1*
1-
1#
#1740
0#
#1745
b11 S
0(
0*
0-
1#
#1750
0#
#1755
b1 S
b111001 N
1#
#1760
0#
#1765
b10 S
b111001 '
b111001 3
b111001 Q
1(
1*
1-
1#
#1770
0#
#1775
b11 S
0(
0*
0-
1#
#1780
0#
#1785
b1 S
b111010 N
1#
#1790
0#
#1795
b10 S
b111010 '
b111010 3
b111010 Q
1(
1*
1-
1#
#1800
0#
#1805
b11 S
0(
0*
0-
1#
#1810
0#
#1815
b1 S
b111011 N
1#
#1820
0#
#1825
b10 S
b111011 '
b111011 3
b111011 Q
1(
1*
1-
1#
#1830
0#
#1835
b11 S
0(
0*
0-
1#
#1840
0#
#1845
b1 S
b111100 N
1#
#1850
0#
#1855
b10 S
b111100 '
b111100 3
b111100 Q
1(
1*
1-
1#
#1860
0#
#1865
b11 S
0(
0*
0-
1#
#1870
0#
#1875
b1 S
b111101 N
1#
#1880
0#
#1885
b10 S
b111101 '
b111101 3
b111101 Q
1(
1*
1-
1#
#1890
0#
#1895
b11 S
0(
0*
0-
1#
#1900
0#
#1905
b1 S
b111110 N
1#
#1910
0#
#1915
b10 S
b111110 '
b111110 3
b111110 Q
1(
1*
1-
1#
#1920
0#
#1925
b11 S
0(
0*
0-
1#
#1930
0#
#1935
b1 S
b111111 N
1#
#1940
0#
#1945
b10 S
b111111 '
b111111 3
b111111 Q
1(
1*
1-
1#
#1950
0#
#1955
b11 S
0(
0*
0-
1#
#1960
0#
#1965
b1 S
b1000000 N
1#
#1970
0#
#1975
b10 S
b1000000 '
b1000000 3
b1000000 Q
1(
1*
1-
1#
#1980
0#
#1985
b11 S
0(
0*
0-
1#
#1990
0#
#1995
b1 S
b1000001 N
1#
#2000
0#
#2005
b10 S
b1000001 '
b1000001 3
b1000001 Q
1(
1*
1-
1#
#2010
0#
#2015
b11 S
0(
0*
0-
1#
#2020
0#
#2025
b1 S
b1000010 N
1#
#2030
0#
#2035
b10 S
b1000010 '
b1000010 3
b1000010 Q
1(
1*
1-
1#
#2040
0#
#2045
b11 S
0(
0*
0-
1#
#2050
0#
#2055
b1 S
b1000011 N
1#
#2060
0#
#2065
b10 S
b1000011 '
b1000011 3
b1000011 Q
1(
1*
1-
1#
#2070
0#
#2075
b11 S
0(
0*
0-
1#
#2080
0#
#2085
b1 S
b1000100 N
1#
#2090
0#
#2095
b10 S
b1000100 '
b1000100 3
b1000100 Q
1(
1*
1-
1#
#2100
0#
#2105
b11 S
0(
0*
0-
1#
#2110
0#
#2115
b1 S
b1000101 N
1#
#2120
0#
#2125
b10 S
b1000101 '
b1000101 3
b1000101 Q
1(
1*
1-
1#
#2130
0#
#2135
b11 S
0(
0*
0-
1#
#2140
0#
#2145
b1 S
b1000110 N
1#
#2150
0#
#2155
b10 S
b1000110 '
b1000110 3
b1000110 Q
1(
1*
1-
1#
#2160
0#
#2165
b11 S
0(
0*
0-
1#
#2170
0#
#2175
b1 S
b1000111 N
1#
#2180
0#
#2185
b10 S
b1000111 '
b1000111 3
b1000111 Q
1(
1*
1-
1#
#2190
0#
#2195
b11 S
0(
0*
0-
1#
#2200
0#
#2205
b1 S
b1001000 N
1#
#2210
0#
#2215
b10 S
b1001000 '
b1001000 3
b1001000 Q
1(
1*
1-
1#
#2220
0#
#2225
b11 S
0(
0*
0-
1#
#2230
0#
#2235
b1 S
b1001001 N
1#
#2240
0#
#2245
b10 S
b1001001 '
b1001001 3
b1001001 Q
1(
1*
1-
1#
#2250
0#
#2255
b11 S
0(
0*
0-
1#
#2260
0#
#2265
b1 S
b1001010 N
1#
#2270
0#
#2275
b10 S
b1001010 '
b1001010 3
b1001010 Q
1(
1*
1-
1#
#2280
0#
#2285
b11 S
0(
0*
0-
1#
#2290
0#
#2295
b1 S
b1001011 N
1#
#2300
0#
#2305
b10 S
b1001011 '
b1001011 3
b1001011 Q
1(
1*
1-
1#
#2310
0#
#2315
b11 S
0(
0*
0-
1#
#2320
0#
#2325
b1 S
b1001100 N
1#
#2330
0#
#2335
b10 S
b1001100 '
b1001100 3
b1001100 Q
1(
1*
1-
1#
#2340
0#
#2345
b11 S
0(
0*
0-
1#
#2350
0#
#2355
b1 S
b1001101 N
1#
#2360
0#
#2365
b10 S
b1001101 '
b1001101 3
b1001101 Q
1(
1*
1-
1#
#2370
0#
#2375
b11 S
0(
0*
0-
1#
#2380
0#
#2385
b1 S
b1001110 N
1#
#2390
0#
#2395
b10 S
b1001110 '
b1001110 3
b1001110 Q
1(
1*
1-
1#
#2400
0#
#2405
b11 S
0(
0*
0-
1#
#2410
0#
#2415
b1 S
b1001111 N
1#
#2420
0#
#2425
b10 S
b1001111 '
b1001111 3
b1001111 Q
1(
1*
1-
1#
#2430
0#
#2435
b11 S
0(
0*
0-
1#
#2440
0#
#2445
b1 S
b1010000 N
1#
#2450
0#
#2455
b10 S
b1010000 '
b1010000 3
b1010000 Q
1(
1*
1-
1#
#2460
0#
#2465
b11 S
0(
0*
0-
1#
#2470
0#
#2475
b1 S
b1010001 N
1#
#2480
0#
#2485
b10 S
b1010001 '
b1010001 3
b1010001 Q
1(
1*
1-
1#
#2490
0#
#2495
b11 S
0(
0*
0-
1#
#2500
0#
#2505
b1 S
b1010010 N
1#
#2510
0#
#2515
b10 S
b1010010 '
b1010010 3
b1010010 Q
1(
1*
1-
1#
#2520
0#
#2525
b11 S
0(
0*
0-
1#
#2530
0#
#2535
b1 S
b1010011 N
1#
#2540
0#
#2545
b10 S
b1010011 '
b1010011 3
b1010011 Q
1(
1*
1-
1#
#2550
0#
#2555
b11 S
0(
0*
0-
1#
#2560
0#
#2565
b1 S
b1010100 N
1#
#2570
0#
#2575
b10 S
b1010100 '
b1010100 3
b1010100 Q
1(
1*
1-
1#
#2580
0#
#2585
b11 S
0(
0*
0-
1#
#2590
0#
#2595
b1 S
b1010101 N
1#
#2600
0#
#2605
b10 S
b1010101 '
b1010101 3
b1010101 Q
1(
1*
1-
1#
#2610
0#
#2615
b11 S
0(
0*
0-
1#
#2620
0#
#2625
b1 S
b1010110 N
1#
#2630
0#
#2635
b10 S
b1010110 '
b1010110 3
b1010110 Q
1(
1*
1-
1#
#2640
0#
#2645
b11 S
0(
0*
0-
1#
#2650
0#
#2655
b1 S
b1010111 N
1#
#2660
0#
#2665
b10 S
b1010111 '
b1010111 3
b1010111 Q
1(
1*
1-
1#
#2670
0#
#2675
b11 S
0(
0*
0-
1#
#2680
0#
#2685
b1 S
b1011000 N
1#
#2690
0#
#2695
b10 S
b1011000 '
b1011000 3
b1011000 Q
1(
1*
1-
1#
#2700
0#
#2705
b11 S
0(
0*
0-
1#
#2710
0#
#2715
b1 S
b1011001 N
1#
#2720
0#
#2725
b10 S
b1011001 '
b1011001 3
b1011001 Q
1(
1*
1-
1#
#2730
0#
#2735
b11 S
0(
0*
0-
1#
#2740
0#
#2745
b1 S
b1011010 N
1#
#2750
0#
#2755
b10 S
b1011010 '
b1011010 3
b1011010 Q
1(
1*
1-
1#
#2760
0#
#2765
b11 S
0(
0*
0-
1#
#2770
0#
#2775
b1 S
b1011011 N
1#
#2780
0#
#2785
b10 S
b1011011 '
b1011011 3
b1011011 Q
1(
1*
1-
1#
#2790
0#
#2795
b11 S
0(
0*
0-
1#
#2800
0#
#2805
b1 S
b1011100 N
1#
#2810
0#
#2815
b10 S
b1011100 '
b1011100 3
b1011100 Q
1(
1*
1-
1#
#2820
0#
#2825
b11 S
0(
0*
0-
1#
#2830
0#
#2835
b1 S
b1011101 N
1#
#2840
0#
